<?xml version="1.0" encoding="UTF-8"?>
<objects serializationModel="Studio.02.02.00">
	<object class="Event" id="{df7c21f6-bf3e-473a-9392-54b510466175}">
		<property name="note" />
		<property name="name">
			<value>gusdead</value>
		</property>
		<property name="outputFormat">
			<value>1</value>
		</property>
		<relationship name="folder">
			<destination>{6b027985-2fe0-4eb4-8794-33b9d6a81bc9}</destination>
		</relationship>
		<relationship name="mixer">
			<destination>{b6ab1ade-7105-4e12-a34f-43eb486e9ebf}</destination>
		</relationship>
		<relationship name="masterTrack">
			<destination>{faa81c10-ce59-47dc-838c-46ed905d37f9}</destination>
		</relationship>
		<relationship name="mixerInput">
			<destination>{31dfbe9f-96b8-4521-822c-02757f65f9bf}</destination>
		</relationship>
		<relationship name="automatableProperties">
			<destination>{7a1ced13-2890-40f2-a063-50713b96e822}</destination>
		</relationship>
		<relationship name="markerTracks">
			<destination>{5886dd7a-7adb-4dd4-95c2-a53754d1ed6b}</destination>
		</relationship>
		<relationship name="groupTracks">
			<destination>{58067129-4f93-4f7f-916b-6427fac52e80}</destination>
		</relationship>
		<relationship name="timeline">
			<destination>{49190934-2366-410c-aca9-b7b9bd761bab}</destination>
		</relationship>
		<relationship name="banks">
			<destination>{64ada51c-2d91-4a87-a4b8-1997efcb023b}</destination>
		</relationship>
	</object>
	<object class="EventMixer" id="{b6ab1ade-7105-4e12-a34f-43eb486e9ebf}">
		<relationship name="masterBus">
			<destination>{7b29cfca-e530-46d2-8ff6-83d014f4c8f5}</destination>
		</relationship>
	</object>
	<object class="MasterTrack" id="{faa81c10-ce59-47dc-838c-46ed905d37f9}">
		<relationship name="mixerGroup">
			<destination>{7b29cfca-e530-46d2-8ff6-83d014f4c8f5}</destination>
		</relationship>
	</object>
	<object class="MixerInput" id="{31dfbe9f-96b8-4521-822c-02757f65f9bf}">
		<relationship name="effectChain">
			<destination>{e1950ff1-8794-4e1b-8e75-198e41f26f64}</destination>
		</relationship>
		<relationship name="panner">
			<destination>{0a768c49-558a-407c-a401-b8de9822da6a}</destination>
		</relationship>
		<relationship name="output">
			<destination>{f18d5877-3d50-41c0-b6c0-9be04ada9938}</destination>
		</relationship>
	</object>
	<object class="EventAutomatableProperties" id="{7a1ced13-2890-40f2-a063-50713b96e822}">
		<property name="dopplerScale">
			<value>0</value>
		</property>
		<property name="minimumDistance">
			<value>0</value>
		</property>
		<property name="maximumDistance">
			<value>2000</value>
		</property>
	</object>
	<object class="MarkerTrack" id="{5886dd7a-7adb-4dd4-95c2-a53754d1ed6b}" />
	<object class="GroupTrack" id="{58067129-4f93-4f7f-916b-6427fac52e80}">
		<relationship name="modules">
			<destination>{729736f1-726c-4d96-a16c-6c534d37c24c}</destination>
		</relationship>
		<relationship name="mixerGroup">
			<destination>{4193016f-5122-479a-a19b-7268f3c6f919}</destination>
		</relationship>
	</object>
	<object class="Timeline" id="{49190934-2366-410c-aca9-b7b9bd761bab}">
		<relationship name="modules">
			<destination>{729736f1-726c-4d96-a16c-6c534d37c24c}</destination>
		</relationship>
	</object>
	<object class="EventMixerMaster" id="{7b29cfca-e530-46d2-8ff6-83d014f4c8f5}">
		<relationship name="effectChain">
			<destination>{a123c5a9-b180-4051-a786-7f6b4306f7e4}</destination>
		</relationship>
		<relationship name="panner">
			<destination>{10df37a5-5c04-4d72-8b1e-82fb6c7775af}</destination>
		</relationship>
		<relationship name="mixer">
			<destination>{b6ab1ade-7105-4e12-a34f-43eb486e9ebf}</destination>
		</relationship>
	</object>
	<object class="MixerBusEffectChain" id="{e1950ff1-8794-4e1b-8e75-198e41f26f64}">
		<relationship name="effects">
			<destination>{d64f0be4-6f0f-4289-87da-fec93eb5767d}</destination>
		</relationship>
	</object>
	<object class="MixerBusPanner" id="{0a768c49-558a-407c-a401-b8de9822da6a}" />
	<object class="SingleSound" id="{729736f1-726c-4d96-a16c-6c534d37c24c}">
		<property name="length">
			<value>3.8203174603174608</value>
		</property>
		<relationship name="audioFile">
			<destination>{d7ee8815-e40c-4290-98ff-a6fe19da1723}</destination>
		</relationship>
	</object>
	<object class="EventMixerGroup" id="{4193016f-5122-479a-a19b-7268f3c6f919}">
		<property name="volume">
			<value>10</value>
		</property>
		<property name="name">
			<value>Audio 1</value>
		</property>
		<relationship name="effectChain">
			<destination>{ec3ea82a-aa56-4953-824c-5adec03b1728}</destination>
		</relationship>
		<relationship name="panner">
			<destination>{f7113cab-13ec-4f1b-bd6a-7bbd942e5dc6}</destination>
		</relationship>
		<relationship name="output">
			<destination>{7b29cfca-e530-46d2-8ff6-83d014f4c8f5}</destination>
		</relationship>
	</object>
	<object class="MixerBusEffectChain" id="{a123c5a9-b180-4051-a786-7f6b4306f7e4}">
		<relationship name="effects">
			<destination>{f34c3b0e-f7b9-40cc-bb2f-11a0be68ed9f}</destination>
		</relationship>
	</object>
	<object class="MixerBusPanner" id="{10df37a5-5c04-4d72-8b1e-82fb6c7775af}" />
	<object class="MixerBusFader" id="{d64f0be4-6f0f-4289-87da-fec93eb5767d}" />
	<object class="MixerBusEffectChain" id="{ec3ea82a-aa56-4953-824c-5adec03b1728}">
		<relationship name="effects">
			<destination>{ff413e85-4ac1-456d-b9ec-df385980c767}</destination>
			<destination>{e11008a1-6ee6-4c7b-a68b-b29074976b7b}</destination>
		</relationship>
	</object>
	<object class="MixerBusPanner" id="{f7113cab-13ec-4f1b-bd6a-7bbd942e5dc6}" />
	<object class="MixerBusFader" id="{f34c3b0e-f7b9-40cc-bb2f-11a0be68ed9f}" />
	<object class="MixerBusFader" id="{ff413e85-4ac1-456d-b9ec-df385980c767}" />
	<object class="ThreeEQEffect" id="{e11008a1-6ee6-4c7b-a68b-b29074976b7b}">
		<property name="highGain">
			<value>5</value>
		</property>
		<property name="crossoverSlope">
			<value>0</value>
		</property>
	</object>
</objects>
